mooshimeter/__init__.py
mooshimeter/bg_wrapper.py
mooshimeter/config_node.py
mooshimeter/meter.py
mooshimeter/utils.py
mooshimeter/vendor/__init__.py
mooshimeter/vendor/bglib.py
mooshimeter-0.1.0.dist-info/License.txt
mooshimeter-0.1.0.dist-info/METADATA
mooshimeter-0.1.0.dist-info/WHEEL
mooshimeter-0.1.0.dist-info/top_level.txt
mooshimeter-0.1.0.dist-info/RECORD
